telivision/__init__.py
telivision/py.typed
telivision/telienums.py
telivision/teliopencv.py
telivision/teliwrap.py
telivision-0.1.3.dist-info/WHEEL
telivision-0.1.3.dist-info/entry_points.txt
telivision-0.1.3.dist-info/METADATA
telivision-0.1.3.dist-info/RECORD
