Metadata-Version: 2.3
Name: telivision
Version: 0.1.3
Summary: Add your description here
Author: Otto Hanski
Author-email: Otto Hanski <otto.hanski@zivid.com>
Requires-Dist: numpy>=2.2.6
Requires-Dist: opencv-python>=4.12.0.88
Requires-Dist: pytelicam
Requires-Python: >=3.13
